grouped_sampling/__init__.py
grouped_sampling/base_pipeline.py
grouped_sampling/completion_dict.py
grouped_sampling/generation_type.py
grouped_sampling/generation_utils.py
grouped_sampling/postprocessor.py
grouped_sampling/preprocessor.py
grouped_sampling/repetition_penalty.py
grouped_sampling/sampling_pipeline.py
grouped_sampling/token_ids.py
grouped_sampling/tree_pipeline.py
grouped_sampling-1.0.2.dist-info/METADATA
grouped_sampling-1.0.2.dist-info/WHEEL
grouped_sampling-1.0.2.dist-info/RECORD
