Metadata-Version: 2.1
Name: grouped_sampling
Version: 1.0.2
Summary: A faster algorithm for generating texts with cuasal language models
Author-email: Yoni Kremer <yoni.kremer@gmail.com>
License-Expression: MIT
Keywords: GPT,NLP,cuasal-language-model,cuasal-text-generation,gpt,language-model,natural-language-processing,nlp,text-generation
Classifier: Intended Audience :: Developers
Classifier: License :: OSI Approved :: MIT License
Classifier: Programming Language :: Python :: 3
Classifier: Topic :: Software Development :: Libraries :: Python Modules
Requires-Python: >=3.6
